certificate/__init__.py
certificate/cert_common.py
certificate/cert_config.py
certificate/cert_data_sim.py
certificate/cert_defines.py
certificate/cert_gw_sim.py
certificate/cert_mqtt.py
certificate/cert_prints.py
certificate/cert_protobuf.py
certificate/cert_results.py
certificate/cert_utils.py
certificate/certificate.py
certificate/certificate_cli.py
certificate/certificate_eth_test_list.txt
certificate/certificate_sanity_test_list.txt
certificate/certificate_test_list.txt
certificate/wlt_types.py
certificate/ag/wlt_cmd_if.html
certificate/ag/wlt_types_ag.py
certificate/tests/calibration/interval_test/interval_test.json
certificate/tests/calibration/interval_test/interval_test.py
certificate/tests/calibration/output_power_test/output_power_test.json
certificate/tests/calibration/output_power_test/output_power_test.py
certificate/tests/calibration/pattern_test/pattern_test.json
certificate/tests/calibration/pattern_test/pattern_test.py
certificate/tests/cloud_connectivity/acl_ext_adv_test/acl_ext_adv_test.json
certificate/tests/cloud_connectivity/acl_ext_adv_test/acl_ext_adv_test.py
certificate/tests/cloud_connectivity/acl_test/acl_test.json
certificate/tests/cloud_connectivity/acl_test/acl_test.py
certificate/tests/cloud_connectivity/brg_ota_test/brg_ota_test.json
certificate/tests/cloud_connectivity/brg_ota_test/brg_ota_test.py
certificate/tests/cloud_connectivity/channel_scan_behaviour_test/channel_scan_behaviour_test.json
certificate/tests/cloud_connectivity/channel_scan_behaviour_test/channel_scan_behaviour_test.py
certificate/tests/cloud_connectivity/connection_test/connection_test.json
certificate/tests/cloud_connectivity/connection_test/connection_test.py
certificate/tests/cloud_connectivity/deduplication_test/deduplication_test.json
certificate/tests/cloud_connectivity/deduplication_test/deduplication_test.py
certificate/tests/cloud_connectivity/downlink_test/downlink_test.json
certificate/tests/cloud_connectivity/downlink_test/downlink_test.py
wiliot_certificate-4.5.0.dist-info/licenses/LICENSE
wiliot_certificate-4.5.0.dist-info/METADATA
wiliot_certificate-4.5.0.dist-info/WHEEL
wiliot_certificate-4.5.0.dist-info/entry_points.txt
wiliot_certificate-4.5.0.dist-info/top_level.txt
wiliot_certificate-4.5.0.dist-info/RECORD
