Metadata-Version: 2.4
Name: wiliot_certificate
Version: 4.5.0
Summary: A library for certifying Wiliot-compliant boards
Author-email: Wiliot <support@wiliot.com>
License-Expression: MIT
Project-URL: Wiliot, https://www.wiliot.com
Project-URL: Certified, https://www.wiliot.com/product/ambient-iot-network#partner-device-certification
Classifier: Programming Language :: Python :: 3
Classifier: Operating System :: OS Independent
Requires-Python: >=3.9
License-File: LICENSE
Requires-Dist: flask>=3.1
Requires-Dist: appdirs>=1.4.4
Requires-Dist: plotly>=6.0.0
Requires-Dist: numpy>=1.21.5
Requires-Dist: pandas>=2.2.3
Requires-Dist: colorama>=0.4.6
Requires-Dist: tabulate>=0.9.0
Requires-Dist: wiliot-core>=5.9.1
Requires-Dist: paho-mqtt>=2.1.0
Requires-Dist: bitstruct>=8.20.0
Requires-Dist: protobuf>=6.30.2
Requires-Dist: wiliot-api>=4.10.8
Requires-Dist: jsonschema>=4.23.0
Requires-Dist: statsmodels>=0.14.4
Requires-Dist: pyserial>=3.5
Requires-Dist: reportlab>=4.3.1
Requires-Dist: google-api-python-client>=2.162.0
Dynamic: license-file
